[{"checked":true,"name":"xscenter","name_ch":"销售中心","nextClass":[
	{"checked":true,"name":"addProduct","name_ch":"客户报价单"},
	{"checked":true,"name":"tijian","name_ch":"客户体检表"},
	{"checked":true,"name":"plan","name_ch":"代客户下计划"},
	{"checked":true,"name":"order","name_ch":"代客户下订单"},
	{"checked":true,"name":"orderTracking","name_ch":"客户订单跟踪"},
	{"checked":true,"name":"orderTracking_operation","name_ch":"客户订单跟踪-操作"},
	{"checked":true,"name":"editOrderNum","name_ch":"修改订单数量"},
	{"checked":true,"name":"editOrderPrice","name_ch":"修改订单单价"},
	{"checked":true,"name":"khysqd","name_ch":"客户收货验收清单"},
	{"checked":false,"name":"salesOrder","name_ch":"销售开单"},
	{"checked":false,"name":"salesOrder_confirm","name_ch":"销售开单-审核"}
]},
{"checked":true,"name":"report","name_ch":"报表中心","nextClass":[
{"checked":true,"name":"plan_report","name_ch":"销售计划统计报表"},
{"checked":true,"name":"plan_excel","name_ch":"计划统计数据-导出"},
{"checked":true,"name":"xl_report","name_ch":"销量统计报表"},
{"checked":true,"name":"xssk_report","name_ch":"销售收款报表"},
{"checked":true,"name":"xl_count_report","name_ch":"销量汇总统计表"},
{"checked":true,"name":"client_dzd","name_ch":"客户对账单"},
{"checked":true,"name":"workPrice","name_ch":"工人工价统计"},
{"checked":true,"name":"workSumPrice","name_ch":"工价汇总统计"}
]},
{"checked":true,"name":"purchase","name_ch":"采购管理","nextClass":[
{"checked":true,"name":"purchase_order","name_ch":"采购订单"},
{"checked":true,"name":"purchase_price","name_ch":"修改采购价格"},
{"checked":true,"name":"purchase_num","name_ch":"修改采购数量"},
{"checked":true,"name":"purchase_gen","name_ch":"下采购订单"},
{"checked":true,"name":"purchase_ruku","name_ch":"采购入库单"},
{"checked":true,"name":"purchase_returnGoods","name_ch":"采购退货单"},
{"checked":true,"name":"purchase_orderTracking","name_ch":"采购订单跟踪表"},
{"checked":true,"name":"purchase_paymentTable","name_ch":"采购付款报表"},
{"checked":true,"name":"purchase_detailAccount","name_ch":"应付明细账"},
{"checked":true,"name":"purchase_procurementStatistical","name_ch":"采购明细统计"},
{"checked":true,"name":"inventory_allocation","name_ch":"库存调拨单"},
{"checked":true,"name":"inventory","name_ch":"期初库存报表"},
{"checked":true,"name":"purchase_ruku_rz","name_ch":"采购入库单-入库"},
{"checked":true,"name":"purchase_tuihuo","name_ch":"采购退货单-退货"},
{"checked":true,"name":"purchase_confirm","name_ch":"采购退货单-审核"}
]},
{"checked":true,"name":"base_data_maintenance","name_ch":"系统控制","nextClass":[
{"checked":true,"name":"system_maintenance","name_ch":"管理模式驾驶舱"},
{"checked":true,"name":"backups_maintenance","name_ch":"备份"},
{"checked":true,"name":"backup_down","name_ch":"下载备份文件"},
{"checked":true,"name":"rcovery","name_ch":"还原"},
{"checked":true,"name":"process_maintenance","name_ch":"定义协同流程"},
{"checked":true,"name":"work_transfer","name_ch":"工作交接"},
{"checked":true,"name":"sgin2","name_ch":"上班签到-手动上传"},
{"checked":true,"name":"signinfo","name_ch":"查看上班签到"},
{"checked":true,"name":"signinfoCount","name_ch":"上班签到汇总"},
{"checked":true,"name":"sellerSigninfo","name_ch":"查看业务员签到"},
{"checked":true,"name":"signinfoAllDept","name_ch":"查看所有部门签到"},
{"checked":true,"name":"signinfoAll","name_ch":"查看所有人签到"},
{"checked":true,"name":"pingfen","name_ch":"日志评分"},
{"checked":true,"name":"noticeList","name_ch":"公告列表"},
{"checked":true,"name":"addNotice","name_ch":"公告增加"},
{"checked":true,"name":"allNotice","name_ch":"查看所有人发布的公告"},
{"checked":true,"name":"delNotice","name_ch":"删除自己公告"},
{"checked":true,"name":"delAllNotice","name_ch":"删除其它人公告"},
{"checked":true,"name":"editNotice","name_ch":"修改自己公告"},
{"checked":true,"name":"editAllNotice","name_ch":"修改其它人公告"}

]},
{"checked":true,"name":"production","name_ch":"生产控制","nextClass":[
{"checked":true,"name":"productionProcess","name_ch":"生产流程定义"},
{"checked":true,"name":"productionPlan","name_ch":"生产计划"},
{"checked":true,"name":"productionTracking","name_ch":"生产计划跟踪"},
{"checked":true,"name":"dispatchingWorkQry","name_ch":"生产派工"},
{"checked":true,"name":"qualityTesting","name_ch":"质检"},
{"checked":true,"name":"productionDel","name_ch":"生产计划删除"},
{"checked":true,"name":"productionXml","name_ch":"生产计划导入"},
{"checked":true,"name":"productionExcel","name_ch":"生产计划导出"}
]},
{"checked":true,"name":"data_maintenance","name_ch":"资料维护","nextClass":[
{"checked":true,"name":"dept_maintenance","name_ch":"部门维护"},
{"checked":true,"name":"queryInventory","name_ch":"期末库存查询"},
{"checked":true,"name":"personnel_maintenance","name_ch":"员工维护"},
{"checked":true,"name":"settlement_maintenance","name_ch":"结算方式维护"},
{"checked":true,"name":"quhua_maintenance","name_ch":"行政区划"},
{"checked":true,"name":"client_maintenance","name_ch":"客户维护"},
{"checked":true,"name":"room_maintenance","name_ch":"库房维护"},
{"checked":true,"name":"class_maintenance","name_ch":"产品类别"},
{"checked":true,"name":"product_maintenance","name_ch":"产品维护"},
{"checked":true,"name":"gys_maintenance","name_ch":"供应商维护"},
{"checked":true,"name":"operate_maintenance","name_ch":"运营商维护"},
{"checked":true,"name":"qichu_maintenance","name_ch":"期初维护"},
{"checked":true,"name":"siji_maintenance","name_ch":"司机维护"},
{"checked":true,"name":"dian_maintenance","name_ch":"电工维护"},
{"checked":true,"name":"brandOfOrigin","name_ch":"产地品牌"},
{"checked":true,"name":"accountingSubjects","name_ch":"会计科目"},
{"checked":true,"name":"add_maintenance","name_ch":"增加"},
{"checked":true,"name":"edit_maintenance","name_ch":"修改"},
{"checked":true,"name":"del_maintenance","name_ch":"删除"}
]}
]